propysition/__init__.py
propysition/main.py
propysition-0.0.1.dist-info/licenses/LICENSE
propysition-0.0.1.dist-info/METADATA
propysition-0.0.1.dist-info/WHEEL
propysition-0.0.1.dist-info/top_level.txt
propysition-0.0.1.dist-info/RECORD
