Metadata-Version: 2.4
Name: propysition
Version: 0.0.1
Summary: A small propositional logic package that can form arguments and generate truth tables. Aimed to be used a tool to speed up propositional logic studying for students.
Author-email: Luuk Unger <luuk.c.unger@gmail.com>
License-Expression: MIT
Project-URL: Homepage, https://github.com/LCUnger/Propysition
Project-URL: Issues, https://github.com/LCUnger/Propysition/issues
Classifier: Programming Language :: Python :: 3
Classifier: Operating System :: OS Independent
Requires-Python: >=3.9
License-File: LICENSE
Requires-Dist: numpy
Requires-Dist: pandas
Dynamic: license-file
